Workbook
Name Comprar: [1]Param!#REF!
Name Periodicidade: [2]Param!$AB$5:$AB$9
Name Status: [1]Param!#REF!
Name VersaoExcel: [2]Param!$D$15:$E$15
Name VersaoSR: [2]Param!$C$24:$C$26

Sheet Capa
B2: Previsões de Orçamento | K2: Lê Ai
C4: 1 | D4: Capa | F4: Instruções, Histórico de Alterações e as Aprovações
C5: =C4+1 -> 2 | D5: Orçado | F5: Detalhamento dos investimentos orçados
C6: =C5+1 -> 3 | D6: Realizado | F6: Detalhamento dos investimentos realizados
C7: =C6+1 -> 4 | D7: Status | F7: Status comparando Orçado x Realizado
C8: =C7+1 -> 5 | D8: Parâmetros | F8: Parâmetros usados nas outras abas da planilha.
B14: Controle de Versões
B15: Versão | C15: Data | D15: Autor | E15: Notas da Revisão
B16: 1.0 | C16: =DATE(2026,10,26) -> 46321 | D16: Renato Douglas Nascimento Silva de Oliveira | E16: Versão inicial: linha de base do TAP nº 01 (R$ 46.420,88) distribuída por mês; realizado de agosto a outubro, data de status 26/10/2026.
B20: Instruções | D20: =TODAY() -> 46321
B21: Ref. | C21: Aba | D21: Respons | E21: Passos
B22: 0 | C22: Param | D22: PMO | E22: Entre com o Custo do Capital
B23: 1 | C23: Orçado | D23: Gerente de Projetos | E23: Preencher as informações de identificação do projeto (Nome, Solicitante e Patrocionador)
B24: =B23+1 -> 2 | C24: Orçado | D24: Gerente de Projetos | E24: Preencher na coluna B o nome de cada Gasto (B7, B10, ...). No máximo 5, caso tiver mais de 5 agrupar os benefícios ou ajustar planilha. Veja na Aba Param - Coluna C - Tipos de gastos comuns em projetos
B25: =B24+1 -> 3 | C25: Orçado | D25: Gerente de Projetos | E25: Sempre que possível, esclareça como foi calculado o valor dos gastos (C7, C10, ...)
B26: =B25+1 -> 4 | C26: Orçado | D26: Gerente de Projetos | E26: Entrar com o valor dos gastos por ano (D9..M21), se preferir, entre com o valor do crescimento por ano (D8..M20) para todos os gastos
B27: =B26+1 -> 5 | C27: Orçado | D27: Gerente de Projetos | E27: Preenche na coluna B o nome dos custos (B29, B30)
B28: =B27+1 -> 6 | C28: Orçado | D28: Gerente de Projetos | E28: Sempre que possível, esclareça como foi calculado o valor dos custos (C29, C30)
B29: =B28+1 -> 7 | C29: Orçado | D29: Gerente de Projetos | E29: Entrar com o valor dos custos por ano (D27..M31)
B30: =B29+1 -> 8 | C30: Realizado | D30: Gerente de Projetos | E30: Entre com o valor realizado mês a mês. Caso não necessitar registrar os detalhes, pode incluir o valor total na linha 39 [Investimento total]
B31: =B30+1 -> 9 | C31: Param | D31: Gerente de Projetos | E31: A cada revisão, atualizar a Data de status e o Último mês com realizado (Param C21:C22). A aba Status deixa os meses seguintes em branco.
B32: =B31+1 -> 10 | C32: Param | D32: Gerente de Projetos | E32: As bases das estimativas (Param C25:C37) alimentam as fórmulas da aba Orcado. Alterá-las muda a linha de base e passa pelo controle de mudança.
B33: =B32+1 -> 11 | C33: Realizado | D33: Gerente de Projetos | E33: Sem apontamento de horas, o realizado repete a base do orçado. Desvio conhecido (horas, gasto efetivo) entra aqui, mês a mês.
B34: =B33+1 -> 12
B36: Aprovações
B37: Ref. | C37: Data | D37: Participante | E37: Assinatura
B38: 1 | D38: Vicenzo Fonseca de Mello Souza (Gerente do Projeto)
B39: 2 | D39: Ana Luiza de Freitas Rodrigues
B40: 3 | D40: Henrique Moreira Gomes de Carvalho
B41: 4 | D41: Kayke Emanoel de Souza Santos
B42: 5 | D42: Renato Douglas Nascimento Silva de Oliveira

Sheet Orcado
B2: Identificação do Projeto | E2: Mês
B3: Nome do Projeto | C3: =Param!C17 -> Lê Ai | E3: =Param!C18 -> 46235 | F3: =DATE(YEAR(E3),MONTH(E3)+1,DAY(E3)) -> 46266 | G3: =DATE(YEAR(F3),MONTH(F3)+1,DAY(F3)) -> 46296 | H3: =DATE(YEAR(G3),MONTH(G3)+1,DAY(G3)) -> 46327 | I3: =DATE(YEAR(H3),MONTH(H3)+1,DAY(H3)) -> 46357 | J3: =DATE(YEAR(I3),MONTH(I3)+1,DAY(I3)) -> 46388 | K3: =DATE(YEAR(J3),MONTH(J3)+1,DAY(J3)) -> 46419 | L3: =DATE(YEAR(K3),MONTH(K3)+1,DAY(K3)) -> 46447 | M3: =DATE(YEAR(L3),MONTH(L3)+1,DAY(L3)) -> 46478 | ... P3: =DATE(YEAR(O3),MONTH(O3)+1,DAY(O3)) -> 46569 | Q3: TOTAL
B4: Patrocinador | C4: =Param!C19 -> Professores orientadores de TI V | D4: 0 | E4: 1 | F4: =E4+1 -> 2 | G4: =F4+1 -> 3 | H4: =G4+1 -> 4 | I4: =H4+1 -> 5 | J4: =I4+1 -> 6 | K4: =J4+1 -> 7 | L4: =K4+1 -> 8 | M4: =L4+1 -> 9 | ... P4: =O4+1 -> 12
B5: Investimento Total | D5: =SUM(D19:D32)+D9+D11+D13+D15+D17 -> 0 | E5: =SUM(E19:E32)+E9+E11+E13+E15+E17 -> 10315.75 | F5: =SUM(F19:F32)+F9+F11+F13+F15+F17 -> 10315.75 | G5: =SUM(G19:G32)+G9+G11+G13+G15+G17 -> 10315.75 | H5: =SUM(H19:H32)+H9+H11+H13+H15+H17 -> 10315.75 | I5: =SUM(I19:I32)+I9+I11+I13+I15+I17 -> 5157.875 | J5: =SUM(J19:J32)+J9+J11+J13+J15+J17 -> 0 | K5: =SUM(K19:K32)+K9+K11+K13+K15+K17 -> 0 | ... P5: =SUM(P19:P32)+P9+P11+P13+P15+P17 -> 0 | Q5: =SUM(D5:P5) -> 46420.875
B6: Investimento Acumulado | D6: =D5 -> 0 | E6: =D6+E5 -> 10315.75 | F6: =E6+F5 -> 20631.5 | G6: =F6+G5 -> 30947.25 | H6: =G6+H5 -> 41263 | I6: =H6+I5 -> 46420.875 | J6: =I6+J5 -> 46420.875 | K6: =J6+K5 -> 46420.875 | L6: =K6+L5 -> 46420.875 | ... P6: =O6+P5 -> 46420.875
B7: Orçado | C7: Explicação
B8: Investimento c/ taxa de crescimento | C8: Para facilitar o cálculo do gasto baseado em uma taxa de crescimento. | F8: 0.1 | G8: =F8 -> 0.1 | H8: =G8 -> 0.1 | I8: =H8 -> 0.1 | J8: =I8 -> 0.1 | K8: =J8 -> 0.1 | L8: =K8 -> 0.1 | M8: =L8 -> 0.1 | N8: =M8 -> 0.1 | ... P8: =O8 -> 0.1
B9: Gasto | E9: 0 | F9: =E9*(1+F8) -> 0 | G9: =F9*(1+G8) -> 0 | H9: =G9*(1+H8) -> 0 | I9: =H9*(1+I8) -> 0 | J9: =I9*(1+J8) -> 0 | K9: =J9*(1+K8) -> 0 | L9: =K9*(1+L8) -> 0 | M9: =L9*(1+M8) -> 0 | ... P9: =O9*(1+P8) -> 0 | Q9: =SUM(D9:P9) -> 0
B10: Taxa de Crescimento | C10: Para facilitar o cálculo do gasto baseado em uma taxa de crescimento. | F10: 0.1 | G10: =F10 -> 0.1 | H10: =G10 -> 0.1 | I10: =H10 -> 0.1 | J10: =I10 -> 0.1 | K10: =J10 -> 0.1 | L10: =K10 -> 0.1 | M10: =L10 -> 0.1 | N10: =M10 -> 0.1 | ... P10: =O10 -> 0.1
B11: Gasto | E11: 0 | F11: =E11*(1+F10) -> 0 | G11: =F11*(1+G10) -> 0 | H11: =G11*(1+H10) -> 0 | I11: =H11*(1+I10) -> 0 | J11: =I11*(1+J10) -> 0 | K11: =J11*(1+K10) -> 0 | L11: =K11*(1+L10) -> 0 | M11: =L11*(1+M10) -> 0 | ... P11: =O11*(1+P10) -> 0 | Q11: =SUM(D11:P11) -> 0
B12: Taxa de Crescimento | C12: Para facilitar o cálculo do gasto baseado em uma taxa de crescimento. | F12: 0.1 | G12: =F12 -> 0.1 | H12: =G12 -> 0.1 | I12: =H12 -> 0.1 | J12: =I12 -> 0.1 | K12: =J12 -> 0.1 | L12: =K12 -> 0.1 | M12: =L12 -> 0.1 | N12: =M12 -> 0.1 | ... P12: =O12 -> 0.1
B13: Gasto | E13: 0 | F13: =E13*(1+F12) -> 0 | G13: =F13*(1+G12) -> 0 | H13: =G13*(1+H12) -> 0 | I13: =H13*(1+I12) -> 0 | J13: =I13*(1+J12) -> 0 | K13: =J13*(1+K12) -> 0 | L13: =K13*(1+L12) -> 0 | M13: =L13*(1+M12) -> 0 | ... P13: =O13*(1+P12) -> 0 | Q13: =SUM(D13:P13) -> 0
B14: Taxa de Crescimento | C14: Para facilitar o cálculo do gasto baseado em uma taxa de crescimento. | F14: 0.1 | G14: =F14 -> 0.1 | H14: =G14 -> 0.1 | I14: =H14 -> 0.1 | J14: =I14 -> 0.1 | K14: =J14 -> 0.1 | L14: =K14 -> 0.1 | M14: =L14 -> 0.1 | N14: =M14 -> 0.1 | ... P14: =O14 -> 0.1
B15: Gasto | E15: 0 | F15: =E15*(1+F14) -> 0 | G15: =F15*(1+G14) -> 0 | H15: =G15*(1+H14) -> 0 | I15: =H15*(1+I14) -> 0 | J15: =I15*(1+J14) -> 0 | K15: =J15*(1+K14) -> 0 | L15: =K15*(1+L14) -> 0 | M15: =L15*(1+M14) -> 0 | ... P15: =O15*(1+P14) -> 0 | Q15: =SUM(D15:P15) -> 0
B16: Taxa de Crescimento | C16: Para facilitar o cálculo do gasto baseado em uma taxa de crescimento. | F16: 0.1 | G16: =F16 -> 0.1 | H16: =G16 -> 0.1 | I16: =H16 -> 0.1 | J16: =I16 -> 0.1 | K16: =J16 -> 0.1 | L16: =K16 -> 0.1 | M16: =L16 -> 0.1 | N16: =M16 -> 0.1 | ... P16: =O16 -> 0.1
B17: Gasto | E17: 0 | F17: =E17*(1+F16) -> 0 | G17: =F17*(1+G16) -> 0 | H17: =G17*(1+H16) -> 0 | I17: =H17*(1+I16) -> 0 | J17: =I17*(1+J16) -> 0 | K17: =J17*(1+K16) -> 0 | L17: =K17*(1+L16) -> 0 | M17: =L17*(1+M16) -> 0 | ... P17: =O17*(1+P16) -> 0 | Q17: =SUM(D17:P17) -> 0
B18: Investimentos
B19: Recursos humanos (equipe) | C19: TAP 4.1: 5 integrantes x 8 h/semana x R$ 45,00/h. 160 h por mês cheio, 80 h em dezembro; 720 h no total. | D19: 0 | E19: =Param!$C$25*Param!$C$26*Param!$C$27*Param!$C$36 -> 7200 | F19: =Param!$C$25*Param!$C$26*Param!$C$27*Param!$C$36 -> 7200 | G19: =Param!$C$25*Param!$C$26*Param!$C$27*Param!$C$36 -> 7200 | H19: =Param!$C$25*Param!$C$26*Param!$C$27*Param!$C$36 -> 7200 | I19: =Param!$C$25*Param!$C$26*Param!$C$27*Param!$C$37 -> 3600 | J19: 0 | K19: 0 | L19: 0 | M19: 0 | N19: 0 | O19: 0 | P19: 0 | Q19: =SUM(D19:P19) -> 32400
B20: Hardware (depreciação) | C20: TAP 4.2: 5 notebooks de uso próprio de R$ 4.500,00, depreciação linear em 48 meses. Meio mês em dezembro. | D20: 0 | E20: =Param!$C$25*Param!$C$31/Param!$C$32*Param!$C$36/Param!$C$36 -> 468.75 | F20: =Param!$C$25*Param!$C$31/Param!$C$32*Param!$C$36/Param!$C$36 -> 468.75 | G20: =Param!$C$25*Param!$C$31/Param!$C$32*Param!$C$36/Param!$C$36 -> 468.75 | H20: =Param!$C$25*Param!$C$31/Param!$C$32*Param!$C$36/Param!$C$36 -> 468.75 | I20: =Param!$C$25*Param!$C$31/Param!$C$32*Param!$C$37/Param!$C$36 -> 234.375 | J20: 0 | K20: 0 | L20: 0 | M20: 0 | N20: 0 | O20: 0 | P20: 0 | Q20: =SUM(D20:P20) -> 2109.375
B21: Rede e hospedagem | C21: TAP 4.3: equivalente dos planos pagos de Render e Neon, US$ 54,00/mês a R$ 5,50. Desembolso efetivo R$ 0,00 (planos gratuitos). | D21: 0 | E21: =Param!$C$33*Param!$C$35*Param!$C$36/Param!$C$36 -> 297 | F21: =Param!$C$33*Param!$C$35*Param!$C$36/Param!$C$36 -> 297 | G21: =Param!$C$33*Param!$C$35*Param!$C$36/Param!$C$36 -> 297 | H21: =Param!$C$33*Param!$C$35*Param!$C$36/Param!$C$36 -> 297 | I21: =Param!$C$33*Param!$C$35*Param!$C$37/Param!$C$36 -> 148.5 | J21: 0 | K21: 0 | L21: 0 | M21: 0 | N21: 0 | O21: 0 | P21: 0 | Q21: =SUM(D21:P21) -> 1336.5
B22: Software de terceiros | C22: TAP 4.4: 5 assinaturas de assistente de IA a US$ 20,00/mês, a R$ 5,50. IDEs, GitHub e ferramenta de design em licença gratuita ou educacional. | D22: 0 | E22: =Param!$C$25*Param!$C$34*Param!$C$35*Param!$C$36/Param!$C$36 -> 550 | F22: =Param!$C$25*Param!$C$34*Param!$C$35*Param!$C$36/Param!$C$36 -> 550 | G22: =Param!$C$25*Param!$C$34*Param!$C$35*Param!$C$36/Param!$C$36 -> 550 | H22: =Param!$C$25*Param!$C$34*Param!$C$35*Param!$C$36/Param!$C$36 -> 550 | I22: =Param!$C$25*Param!$C$34*Param!$C$35*Param!$C$37/Param!$C$36 -> 275 | J22: 0 | K22: 0 | L22: 0 | M22: 0 | N22: 0 | O22: 0 | P22: 0 | Q22: =SUM(D22:P22) -> 2475
B23: Serviços e treinamento | C23: TAP 4.5: orientação docente, 3 professores x 1 h/semana x R$ 150,00/h. 54 h no total. | D23: 0 | E23: =Param!$C$28*Param!$C$29*Param!$C$30*Param!$C$36 -> 1800 | F23: =Param!$C$28*Param!$C$29*Param!$C$30*Param!$C$36 -> 1800 | G23: =Param!$C$28*Param!$C$29*Param!$C$30*Param!$C$36 -> 1800 | H23: =Param!$C$28*Param!$C$29*Param!$C$30*Param!$C$36 -> 1800 | I23: =Param!$C$28*Param!$C$29*Param!$C$30*Param!$C$37 -> 900 | J23: 0 | K23: 0 | L23: 0 | M23: 0 | N23: 0 | O23: 0 | P23: 0 | Q23: =SUM(D23:P23) -> 8100
B24: Custo | Q24: =SUM(D24:P24) -> 0
B25: Custo | Q25: =SUM(D25:P25) -> 0
B26: Custo | Q26: =SUM(D26:P26) -> 0
B27: Custo | Q27: =SUM(D27:P27) -> 0
B28: Custo | Q28: =SUM(D28:P28) -> 0
B29: Custo | Q29: =SUM(D29:P29) -> 0
B30: Custo | Q30: =SUM(D30:P30) -> 0
B31: Custo | Q31: =SUM(D31:P31) -> 0
B32: Reserva de contingência | C32: Sem reserva financeira: a contingência do projeto é de escopo. O que não termina desce de prioridade e as 7 features opcionais absorvem o atraso. | D32: 0 | E32: 0 | F32: 0 | G32: 0 | H32: 0 | I32: 0 | J32: 0 | K32: 0 | L32: 0 | M32: 0 | N32: 0 | O32: 0 | P32: 0 | Q32: =SUM(D32:P32) -> 0
B37: Indicadores Financeiros
B39: Valor presente dos custos | C39: Custo do capital de 6% a.a. (Param D4), convertido para taxa mensal. | D39: =NPV((1+Param!$D$4)^(1/12)-1,E5:P5)+D5 -> 45799.879
B40: Payback | C40: O projeto não gera receita: monetização está fora do escopo (Declaração de Escopo 3.3). | D40: Não se aplica
B41: ROI | C41: Idem: sem benefício financeiro não há retorno sobre o investimento. | D41: Não se aplica

Sheet Realizado
B2: =Orcado!B2 -> Identificação do Projeto | E2: Mês
B3: Nome do Projeto | C3: =Param!C17 -> Lê Ai | E3: =Orcado!E3 -> 46235 | F3: =Orcado!F3 -> 46266 | G3: =Orcado!G3 -> 46296 | H3: =Orcado!H3 -> 46327 | I3: =Orcado!I3 -> 46357 | J3: =Orcado!J3 -> 46388 | K3: =Orcado!K3 -> 46419 | L3: =Orcado!L3 -> 46447 | ... P3: =Orcado!P3 -> 46569 | Q3: TOTAL
B4: Patrocinador | C4: =Param!C19 -> Professores orientadores de TI V | D4: 0 | E4: 1 | F4: =E4+1 -> 2 | G4: =F4+1 -> 3 | H4: =G4+1 -> 4 | I4: =H4+1 -> 5 | J4: =I4+1 -> 6 | K4: =J4+1 -> 7 | L4: =K4+1 -> 8 | M4: =L4+1 -> 9 | ... P4: =O4+1 -> 12
B5: Investimento Total | D5: =SUM(D19:D32)+D9+D11+D13+D15+D17 -> 0 | E5: =SUM(E19:E32)+E9+E11+E13+E15+E17 -> 10315.75 | F5: =SUM(F19:F32)+F9+F11+F13+F15+F17 -> 10315.75 | G5: =SUM(G19:G32)+G9+G11+G13+G15+G17 -> 10315.75 | H5: =SUM(H19:H32)+H9+H11+H13+H15+H17 -> 0 | I5: =SUM(I19:I32)+I9+I11+I13+I15+I17 -> 0 | J5: =SUM(J19:J32)+J9+J11+J13+J15+J17 -> 0 | K5: =SUM(K19:K32)+K9+K11+K13+K15+K17 -> 0 | ... P5: =SUM(P19:P32)+P9+P11+P13+P15+P17 -> 0 | Q5: =SUM(D5:P5) -> 30947.25
B6: Investimento Acumulado | D6: =D5 -> 0 | E6: =D6+E5 -> 10315.75 | F6: =E6+F5 -> 20631.5 | G6: =F6+G5 -> 30947.25 | H6: =G6+H5 -> 30947.25 | I6: =H6+I5 -> 30947.25 | J6: =I6+J5 -> 30947.25 | K6: =J6+K5 -> 30947.25 | L6: =K6+L5 -> 30947.25 | ... P6: =O6+P5 -> 30947.25
B7: Realizado | C7: Explicação
B8: Investimento c/ taxa de crescimento
B9: =Orcado!B9 -> Gasto | E9: 0 | F9: =E9*(1+F8) -> 0 | G9: =F9*(1+G8) -> 0 | H9: =G9*(1+H8) -> 0 | I9: =H9*(1+I8) -> 0 | J9: =I9*(1+J8) -> 0 | K9: =J9*(1+K8) -> 0 | L9: =K9*(1+L8) -> 0 | M9: =L9*(1+M8) -> 0 | ... P9: =O9*(1+P8) -> 0 | Q9: =SUM(D9:P9) -> 0
B11: =Orcado!B11 -> Gasto | E11: 0 | F11: =E11*(1+F10) -> 0 | G11: =F11*(1+G10) -> 0 | H11: =G11*(1+H10) -> 0 | I11: =H11*(1+I10) -> 0 | J11: =I11*(1+J10) -> 0 | K11: =J11*(1+K10) -> 0 | L11: =K11*(1+L10) -> 0 | M11: =L11*(1+M10) -> 0 | ... P11: =O11*(1+P10) -> 0 | Q11: =SUM(D11:P11) -> 0
B13: =Orcado!B13 -> Gasto | E13: 0 | F13: =E13*(1+F12) -> 0 | G13: =F13*(1+G12) -> 0 | H13: =G13*(1+H12) -> 0 | I13: =H13*(1+I12) -> 0 | J13: =I13*(1+J12) -> 0 | K13: =J13*(1+K12) -> 0 | L13: =K13*(1+L12) -> 0 | M13: =L13*(1+M12) -> 0 | ... P13: =O13*(1+P12) -> 0 | Q13: =SUM(D13:P13) -> 0
B15: =Orcado!B15 -> Gasto | E15: 0 | F15: =E15*(1+F14) -> 0 | G15: =F15*(1+G14) -> 0 | H15: =G15*(1+H14) -> 0 | I15: =H15*(1+I14) -> 0 | J15: =I15*(1+J14) -> 0 | K15: =J15*(1+K14) -> 0 | L15: =K15*(1+L14) -> 0 | M15: =L15*(1+M14) -> 0 | ... P15: =O15*(1+P14) -> 0 | Q15: =SUM(D15:P15) -> 0
B17: =Orcado!B17 -> Gasto | E17: 0 | F17: =E17*(1+F16) -> 0 | G17: =F17*(1+G16) -> 0 | H17: =G17*(1+H16) -> 0 | I17: =H17*(1+I16) -> 0 | J17: =I17*(1+J16) -> 0 | K17: =J17*(1+K16) -> 0 | L17: =K17*(1+L16) -> 0 | M17: =L17*(1+M16) -> 0 | ... P17: =O17*(1+P16) -> 0 | Q17: =SUM(D17:P17) -> 0
B18: Investimentos
B19: =Orcado!B19 -> Recursos humanos (equipe) | C19: Sem apontamento de horas: realizado considerado igual ao orçado, na mesma base. Desembolso efetivo R$ 0,00. | D19: 0 | E19: =Orcado!E19 -> 7200 | F19: =Orcado!F19 -> 7200 | G19: =Orcado!G19 -> 7200 | Q19: =SUM(D19:P19) -> 21600
B20: =Orcado!B20 -> Hardware (depreciação) | C20: Sem apontamento de horas: realizado considerado igual ao orçado, na mesma base. Desembolso efetivo R$ 0,00. | D20: 0 | E20: =Orcado!E20 -> 468.75 | F20: =Orcado!F20 -> 468.75 | G20: =Orcado!G20 -> 468.75 | Q20: =SUM(D20:P20) -> 1406.25
B21: =Orcado!B21 -> Rede e hospedagem | C21: Sem apontamento de horas: realizado considerado igual ao orçado, na mesma base. Desembolso efetivo R$ 0,00. | D21: 0 | E21: =Orcado!E21 -> 297 | F21: =Orcado!F21 -> 297 | G21: =Orcado!G21 -> 297 | Q21: =SUM(D21:P21) -> 891
B22: =Orcado!B22 -> Software de terceiros | C22: Sem apontamento de horas: realizado considerado igual ao orçado, na mesma base. Desembolso efetivo R$ 0,00. | D22: 0 | E22: =Orcado!E22 -> 550 | F22: =Orcado!F22 -> 550 | G22: =Orcado!G22 -> 550 | Q22: =SUM(D22:P22) -> 1650
B23: =Orcado!B23 -> Serviços e treinamento | C23: Sem apontamento de horas: realizado considerado igual ao orçado, na mesma base. Desembolso efetivo R$ 0,00. | D23: 0 | E23: =Orcado!E23 -> 1800 | F23: =Orcado!F23 -> 1800 | G23: =Orcado!G23 -> 1800 | Q23: =SUM(D23:P23) -> 5400
B24: =Orcado!B24 -> Custo | Q24: =SUM(D24:P24) -> 0
B25: =Orcado!B25 -> Custo | Q25: =SUM(D25:P25) -> 0
B26: =Orcado!B26 -> Custo | Q26: =SUM(D26:P26) -> 0
B27: =Orcado!B27 -> Custo | Q27: =SUM(D27:P27) -> 0
B28: =Orcado!B28 -> Custo | Q28: =SUM(D28:P28) -> 0
B29: =Orcado!B29 -> Custo | Q29: =SUM(D29:P29) -> 0
B30: =Orcado!B30 -> Custo | Q30: =SUM(D30:P30) -> 0
B31: =Orcado!B31 -> Custo | Q31: =SUM(D31:P31) -> 0
B32: =Orcado!B32 -> Reserva de contingência | C32: Nenhuma reserva acionada. | D32: 0 | E32: 0 | F32: 0 | G32: 0 | Q32: =SUM(D32:P32) -> 0
B37: Indicadores Financeiros
B39: Valor presente dos custos | C39: Custo do capital de 6% a.a. (Param D4), convertido para taxa mensal. | D39: =NPV((1+Param!$D$4)^(1/12)-1,E5:P5)+D5 -> 30648.402
B40: Payback | C40: O projeto não gera receita: monetização está fora do escopo (Declaração de Escopo 3.3). | D40: Não se aplica
B41: ROI | C41: Idem: sem benefício financeiro não há retorno sobre o investimento. | D41: Não se aplica

Sheet Status
B2: Períodos | C2: No Período (R$) | E2: Acumulado (R$) | G2: Desvio (R$) | H2: Desvio %
B3: Mês | C3: Orçado | D3: Realizado | E3: Orçado | F3: Realizado
B4: 0 | C4: =HLOOKUP($B4,Orcado!$D$4:$P$5,2,FALSE) -> 0 | D4: =IF($B4>Param!$C$22,"",HLOOKUP($B4,Realizado!$D$4:$P$5,2,FALSE)) -> 0 | E4: =C4 -> 0 | F4: =D4 -> 0 | G4: =IF(ISNA(F4),"",F4-E4) -> 0 | H4: =IF(ISNA(F4),"",IF(E4=0,"",F4/E4-1))
B5: =B4+1 -> 1 | C5: =HLOOKUP($B5,Orcado!$D$4:$P$5,2,FALSE) -> 10315.75 | D5: =IF($B5>Param!$C$22,"",HLOOKUP($B5,Realizado!$D$4:$P$5,2,FALSE)) -> 10315.75 | E5: =E4+C5 -> 10315.75 | F5: =IF($B5>Param!$C$22,NA(),F4+D5) -> 10315.75 | G5: =IF(ISNA(F5),"",F5-E5) -> 0 | H5: =IF(ISNA(F5),"",IF(E5=0,"",F5/E5-1)) -> 0
B6: =B5+1 -> 2 | C6: =HLOOKUP($B6,Orcado!$D$4:$P$5,2,FALSE) -> 10315.75 | D6: =IF($B6>Param!$C$22,"",HLOOKUP($B6,Realizado!$D$4:$P$5,2,FALSE)) -> 10315.75 | E6: =E5+C6 -> 20631.5 | F6: =IF($B6>Param!$C$22,NA(),F5+D6) -> 20631.5 | G6: =IF(ISNA(F6),"",F6-E6) -> 0 | H6: =IF(ISNA(F6),"",IF(E6=0,"",F6/E6-1)) -> 0
B7: =B6+1 -> 3 | C7: =HLOOKUP($B7,Orcado!$D$4:$P$5,2,FALSE) -> 10315.75 | D7: =IF($B7>Param!$C$22,"",HLOOKUP($B7,Realizado!$D$4:$P$5,2,FALSE)) -> 10315.75 | E7: =E6+C7 -> 30947.25 | F7: =IF($B7>Param!$C$22,NA(),F6+D7) -> 30947.25 | G7: =IF(ISNA(F7),"",F7-E7) -> 0 | H7: =IF(ISNA(F7),"",IF(E7=0,"",F7/E7-1)) -> 0
B8: =B7+1 -> 4 | C8: =HLOOKUP($B8,Orcado!$D$4:$P$5,2,FALSE) -> 10315.75 | D8: =IF($B8>Param!$C$22,"",HLOOKUP($B8,Realizado!$D$4:$P$5,2,FALSE)) | E8: =E7+C8 -> 41263 | F8: =IF($B8>Param!$C$22,NA(),F7+D8) -> #N/A | G8: =IF(ISNA(F8),"",F8-E8) | H8: =IF(ISNA(F8),"",IF(E8=0,"",F8/E8-1))
B9: =B8+1 -> 5 | C9: =HLOOKUP($B9,Orcado!$D$4:$P$5,2,FALSE) -> 5157.875 | D9: =IF($B9>Param!$C$22,"",HLOOKUP($B9,Realizado!$D$4:$P$5,2,FALSE)) | E9: =E8+C9 -> 46420.875 | F9: =IF($B9>Param!$C$22,NA(),F8+D9) -> #N/A | G9: =IF(ISNA(F9),"",F9-E9) | H9: =IF(ISNA(F9),"",IF(E9=0,"",F9/E9-1))
B10: =B9+1 -> 6 | C10: =HLOOKUP($B10,Orcado!$D$4:$P$5,2,FALSE) -> 0 | D10: =IF($B10>Param!$C$22,"",HLOOKUP($B10,Realizado!$D$4:$P$5,2,FALSE)) | E10: =E9+C10 -> 46420.875 | F10: =IF($B10>Param!$C$22,NA(),F9+D10) -> #N/A | G10: =IF(ISNA(F10),"",F10-E10) | H10: =IF(ISNA(F10),"",IF(E10=0,"",F10/E10-1))
B11: =B10+1 -> 7 | C11: =HLOOKUP($B11,Orcado!$D$4:$P$5,2,FALSE) -> 0 | D11: =IF($B11>Param!$C$22,"",HLOOKUP($B11,Realizado!$D$4:$P$5,2,FALSE)) | E11: =E10+C11 -> 46420.875 | F11: =IF($B11>Param!$C$22,NA(),F10+D11) -> #N/A | G11: =IF(ISNA(F11),"",F11-E11) | H11: =IF(ISNA(F11),"",IF(E11=0,"",F11/E11-1))
B12: =B11+1 -> 8 | C12: =HLOOKUP($B12,Orcado!$D$4:$P$5,2,FALSE) -> 0 | D12: =IF($B12>Param!$C$22,"",HLOOKUP($B12,Realizado!$D$4:$P$5,2,FALSE)) | E12: =E11+C12 -> 46420.875 | F12: =IF($B12>Param!$C$22,NA(),F11+D12) -> #N/A | G12: =IF(ISNA(F12),"",F12-E12) | H12: =IF(ISNA(F12),"",IF(E12=0,"",F12/E12-1))
B13: =B12+1 -> 9 | C13: =HLOOKUP($B13,Orcado!$D$4:$P$5,2,FALSE) -> 0 | D13: =IF($B13>Param!$C$22,"",HLOOKUP($B13,Realizado!$D$4:$P$5,2,FALSE)) | E13: =E12+C13 -> 46420.875 | F13: =IF($B13>Param!$C$22,NA(),F12+D13) -> #N/A | G13: =IF(ISNA(F13),"",F13-E13) | H13: =IF(ISNA(F13),"",IF(E13=0,"",F13/E13-1))
B14: =B13+1 -> 10 | C14: =HLOOKUP($B14,Orcado!$D$4:$P$5,2,FALSE) -> 0 | D14: =IF($B14>Param!$C$22,"",HLOOKUP($B14,Realizado!$D$4:$P$5,2,FALSE)) | E14: =E13+C14 -> 46420.875 | F14: =IF($B14>Param!$C$22,NA(),F13+D14) -> #N/A | G14: =IF(ISNA(F14),"",F14-E14) | H14: =IF(ISNA(F14),"",IF(E14=0,"",F14/E14-1))
B15: =B14+1 -> 11 | C15: =HLOOKUP($B15,Orcado!$D$4:$P$5,2,FALSE) -> 0 | D15: =IF($B15>Param!$C$22,"",HLOOKUP($B15,Realizado!$D$4:$P$5,2,FALSE)) | E15: =E14+C15 -> 46420.875 | F15: =IF($B15>Param!$C$22,NA(),F14+D15) -> #N/A | G15: =IF(ISNA(F15),"",F15-E15) | H15: =IF(ISNA(F15),"",IF(E15=0,"",F15/E15-1))
B16: =B15+1 -> 12 | C16: =HLOOKUP($B16,Orcado!$D$4:$P$5,2,FALSE) -> 0 | D16: =IF($B16>Param!$C$22,"",HLOOKUP($B16,Realizado!$D$4:$P$5,2,FALSE)) | E16: =E15+C16 -> 46420.875 | F16: =IF($B16>Param!$C$22,NA(),F15+D16) -> #N/A | G16: =IF(ISNA(F16),"",F16-E16) | H16: =IF(ISNA(F16),"",IF(E16=0,"",F16/E16-1))
B17: Total | C17: =SUM(C4:C16) -> 46420.875 | D17: =SUM(D4:D16) -> 30947.25
B18: Saldo Final | C18: =C17-D17 -> 15473.625
B19: Realizado até o mês 3 (outubro/2026), data de status 26/10/2026. Meses seguintes ficam em branco até serem realizados.

Sheet Param
B2: Variável | C2: Tipo de Benefício | D2: Custo do Capital
B3: Explicação | D3: Retorno Requerido do Investimento
B4: Domínio ou Valor | C4: Aumento de Receita | D4: 0.06
C5: Aumento de Produtividade
C6: Aumento da Capacidade Produtiva
C7: Redução do Turn-over
C8: Redução de retrabalho
C9: Redução dos custos da não qualidade
C10: Redução das reclamações dos clientes
C11: Redução dos custos
B15: Parametros a serem configurados inicialmente
B16: Projeto
B17: Nome do projeto | C17: Lê Ai
B18: Mês de início | C18: =DATE(2026,8,1) -> 46235
B19: Patrocinador | C19: Professores orientadores de TI V
B20: Status
B21: Data de status | C21: =DATE(2026,10,26) -> 46321
B22: Último mês com realizado (nº do mês; 3 = outubro/2026) | C22: 3
B24: Bases das estimativas (TAP nº 01, item 4)
B25: Integrantes da equipe | C25: 5
B26: Horas semanais por integrante | C26: 8
B27: Valor-hora da equipe (R$) | C27: 45
B28: Professores orientadores | C28: 3
B29: Horas semanais de orientação por professor | C29: 1
B30: Valor-hora da orientação docente (R$) | C30: 150
B31: Valor de cada notebook (R$) | C31: 4500
B32: Vida útil do notebook para depreciação (meses) | C32: 48
B33: Equivalente dos planos pagos Render + Neon (US$/mês) | C33: 54
B34: Assinatura de assistente de IA (US$/mês por integrante) | C34: 20
B35: Câmbio (R$ por US$) | C35: 5.5
B36: Semanas de esforço por mês cheio (ago a nov) | C36: 4
B37: Semanas de esforço em dezembro (1 a 15/12) | C37: 2
